pycnpj_crawler/__init__.py
pycnpj_crawler/crawler.py
pycnpj_crawler/states/__init__.py
pycnpj_crawler/states/ba.py
pycnpj_crawler/states/crawling.py
pycnpj_crawler/states/util.py
pycnpj_crawler-0.1.0.dist-info/WHEEL
pycnpj_crawler-0.1.0.dist-info/METADATA
pycnpj_crawler-0.1.0.dist-info/RECORD
